pygameControls/__init__.py
pygameControls/controller.py
pygameControls/controlsbase.py
pygameControls/dualsense_controller.py
pygameControls/dualsense_edge_controller.py
pygameControls/enums.py
pygameControls/generic_controller.py
pygameControls/globals.py
pygameControls/logitech_dual_action_controller.py
pygameControls/logitech_f310_controller.py
pygameControls/logitech_f510_controller.py
pygameControls/logitech_f710_controller.py
pygameControls/playstation3_controller.py
pygameControls/playstation4_controller.py
pygameControls/sony_playstation3_controller.py
pygameControls/sony_playstation4_controller.py
pygameControls/xbox_360_controller.py
pygameControls/xbox_series_x_controller.py
pygamecontrols-0.2.7.dist-info/licenses/LICENSE
pygamecontrols-0.2.7.dist-info/METADATA
pygamecontrols-0.2.7.dist-info/WHEEL
pygamecontrols-0.2.7.dist-info/top_level.txt
pygamecontrols-0.2.7.dist-info/RECORD
